CircuitCalculator/PlottingTemplates.py
CircuitCalculator/__init__.py
CircuitCalculator/dump_load.py
CircuitCalculator/Circuit/__init__.py
CircuitCalculator/Circuit/circuit.py
CircuitCalculator/Circuit/dump_load.py
CircuitCalculator/Circuit/impedance.py
CircuitCalculator/Circuit/solution.py
CircuitCalculator/Circuit/state_space_model.py
CircuitCalculator/Circuit/symbolic_transformers.py
CircuitCalculator/Circuit/transformers.py
CircuitCalculator/Circuit/Components/__init__.py
CircuitCalculator/Circuit/Components/components.py
CircuitCalculator/Circuit/Components/symbolic_components.py
CircuitCalculator/Display/ScientificFloat.py
CircuitCalculator/Network/elements.py
CircuitCalculator/Network/equivalent_sources.py
CircuitCalculator/Network/loaders.py
CircuitCalculator/Network/network.py
CircuitCalculator/Network/norten_thevenin_elements.py
CircuitCalculator/Network/solution.py
CircuitCalculator/Network/symbolic_elements.py
CircuitCalculator/Network/transformers.py
CircuitCalculator/Network/NodalAnalysis/label_mapping.py
CircuitCalculator/Network/NodalAnalysis/matrix_operations.py
CircuitCalculator/Network/NodalAnalysis/network_analysis.py
CircuitCalculator/Network/NodalAnalysis/node_analysis.py
CircuitCalculator/Network/NodalAnalysis/node_analysis_calculations.py
CircuitCalculator/Network/NodalAnalysis/solution.py
CircuitCalculator/Network/NodalAnalysis/state_space_model.py
CircuitCalculator/SignalProcessing/__init__.py
CircuitCalculator/SignalProcessing/one_sided_functions.py
CircuitCalculator/SignalProcessing/periodic_functions.py
CircuitCalculator/SignalProcessing/state_space_model.py
CircuitCalculator/SignalProcessing/types.py
CircuitCalculator/SimpleAnalysis/FrequencyDomain.py
CircuitCalculator/SimpleAnalysis/NyquistDiagram.py
CircuitCalculator/SimpleAnalysis/PointerDiagram.py
CircuitCalculator/SimpleAnalysis/TimeSeries.py
CircuitCalculator/SimpleAnalysis/__init__.py
CircuitCalculator/SimpleAnalysis/layout.py
CircuitCalculator/SimpleAnalysis/plot_elements.py
circuitcalculator-0.4.17.dist-info/licenses/LICENSE
circuitcalculator-0.4.17.dist-info/METADATA
circuitcalculator-0.4.17.dist-info/WHEEL
circuitcalculator-0.4.17.dist-info/top_level.txt
circuitcalculator-0.4.17.dist-info/RECORD
