Metadata-Version: 2.4
Name: CircuitCalculator
Version: 0.4.17
Summary: Library for analysing and calculating electric networks.
Requires-Python: >=3.10
License-File: LICENSE
Requires-Dist: numpy>=1.26.4
Requires-Dist: scipy>=1.12.0
Requires-Dist: sympy>=1.12
Requires-Dist: matplotlib>=3.5.2
Requires-Dist: schemdraw==0.19
Requires-Dist: PyYAML>=6.0.1
Dynamic: license-file
